subtaitles/__init__.py
subtaitles/cache.py
subtaitles/cli.py
subtaitles/environment.py
subtaitles/exceptions.py
subtaitles/filesystem.py
subtaitles/imports.py
subtaitles/language.py
subtaitles/providers/__init__.py
subtaitles/providers/libretranslate.py
subtaitles/providers/openai.py
subtaitles/providers/protocol.py
subtaitles/providers/pyd_ai.py
subtaitles/srt.py
subtaitles/task.py
subtaitles/translate.py
subt_ai_tles-0.0.7.dist-info/WHEEL
subt_ai_tles-0.0.7.dist-info/entry_points.txt
subt_ai_tles-0.0.7.dist-info/METADATA
subt_ai_tles-0.0.7.dist-info/RECORD
