Metadata-Version: 2.3
Name: subt-ai-tles
Version: 0.0.7
Summary: 
Author: xyzjonas
Author-email: xyzjonas <you@example.com>
License: MIT
Requires-Dist: openai>=1.3.6,<2.0.0
Requires-Dist: libretranslatepy>=2.1.3,<3.0.0
Requires-Dist: pysrt>=1.1.2,<2.0.0
Requires-Dist: deepl>=1.16.1,<2.0.0
Requires-Dist: srt>=3.5.3,<4.0.0
Requires-Dist: pydantic-settings>=2.10.1
Requires-Dist: pydantic-ai-slim[openai]>=1.0.10
Requires-Dist: diskcache>=5.6.3
Requires-Python: >=3.10
Project-URL: Homepage, https://github.com/xyzjonas/subt-ai-tles
